p4async/__init__.py
p4async/py.typed
p4async-0.1.6.dist-info/METADATA
p4async-0.1.6.dist-info/WHEEL
p4async-0.1.6.dist-info/licenses/LICENSE
p4async-0.1.6.dist-info/RECORD
