Metadata-Version: 2.4
Name: p4async
Version: 0.1.6
Summary: An async extension to p4python
Project-URL: Homepage, https://github.com/kristjanvalur/p4async
Project-URL: Issues, https://github.com/kristjanvalue/p4async/issues
Author-email: Kristján Valur Jónsson <sweskman@gmail.com>
License-Expression: MIT
License-File: LICENSE
Classifier: Operating System :: OS Independent
Classifier: Programming Language :: Python :: 3
Requires-Python: >=3.11
Requires-Dist: p4python>=2020.1.0
Provides-Extra: dev
Requires-Dist: pytest-asyncio>=0.22; extra == 'dev'
Requires-Dist: pytest>=7.0; extra == 'dev'
